LICENSE
README.md
setup.py
aiolite/__init__.py
aiolite/_version.py
aiolite/context.py
aiolite/core.py
aiolite/cursor.py
aiolite/exceptions.py
aiolite/factory.py
aiolite/pool.py
aiolite/transaction.py
aiolite.egg-info/PKG-INFO
aiolite.egg-info/SOURCES.txt
aiolite.egg-info/dependency_links.txt
aiolite.egg-info/requires.txt
aiolite.egg-info/top_level.txt