Metadata-Version: 2.1
Name: aiolite
Version: 1.5.4
Summary: A simple asynchronous wrapper for sqlite3
Home-page: https://github.com/Vladyslav49/aiolite
Author: Vladyslav49
License: MIT
Requires-Python: >=3.7
License-File: LICENSE
